LICENSE
README.md
enum_deprecation/__init__.py
enum_deprecation/_enum_deprecation.py
enum_deprecation/_enum_deprecation.pyi
enum_deprecation/py.typed
enum_deprecation-0.1.0.dist-info/METADATA
enum_deprecation-0.1.0.dist-info/WHEEL
enum_deprecation-0.1.0.dist-info/licenses/LICENSE
enum_deprecation-0.1.0.dist-info/RECORD
