Metadata-Version: 2.4
Name: enum-deprecation
Version: 0.1.0
Summary: Deprecate individual Enum members with warnings, for Enum/IntEnum/StrEnum/custom mixins.
License-Expression: MIT
License-File: LICENSE
Keywords: enum,deprecation,warnings,typing,mypy,pep561
Author: Marcin Kornat
Author-email: marcin.kornat@gmail.com
Requires-Python: >=3.11,<4.0
Classifier: License :: OSI Approved :: MIT License
Classifier: Programming Language :: Python
Classifier: Programming Language :: Python :: 3
Classifier: Programming Language :: Python :: 3.11
Classifier: Programming Language :: Python :: 3.12
Classifier: Programming Language :: Python :: 3.13
Classifier: Typing :: Typed
